covalent_blueprints_ai/__init__.py
covalent_blueprints_ai/_prefix.py
covalent_blueprints_ai/_versions.py
covalent_blueprints_ai/database.py
covalent_blueprints_ai/secrets.py
covalent_blueprints_ai/llama_chatbot/__init__.py
covalent_blueprints_ai/llama_chatbot/llama_chatbot.py
covalent_blueprints_ai/llama_chatbot/_src/_llama_chatbot.py
covalent_blueprints_ai/lora_fine_tuning/__init__.py
covalent_blueprints_ai/lora_fine_tuning/lora_fine_tuning.py
covalent_blueprints_ai/lora_fine_tuning/utilities.py
covalent_blueprints_ai/lora_fine_tuning/_src/_lora_fine_tuning.py
covalent_blueprints_ai/nvidia_llama_rag/__init__.py
covalent_blueprints_ai/nvidia_llama_rag/nvidia_llama_rag.py
covalent_blueprints_ai/nvidia_llama_rag/_src/_nvidia_llama_rag.py
covalent_blueprints_ai/sdxl/__init__.py
covalent_blueprints_ai/sdxl/sdxl.py
covalent_blueprints_ai/sdxl/_src/_sdxl.py
covalent_blueprints_ai/sdxl_turbo/__init__.py
covalent_blueprints_ai/sdxl_turbo/sdxl_turbo.py
covalent_blueprints_ai/sdxl_turbo/_src/_sdxl_turbo.py
covalent_blueprints_ai/vllm_inference/__init__.py
covalent_blueprints_ai/vllm_inference/vllm_inference.py
covalent_blueprints_ai/vllm_inference/_src/_vllm_inference.py
covalent_blueprints_ai-0.5.2.dist-info/licenses/LICENSE
debug/print_bp.py
debug/refactor_cov.py
docs/scrap.py
tests/__init__.py
tests/test_summaries.py
covalent_blueprints_ai-0.5.2.dist-info/METADATA
covalent_blueprints_ai-0.5.2.dist-info/WHEEL
covalent_blueprints_ai-0.5.2.dist-info/top_level.txt
covalent_blueprints_ai-0.5.2.dist-info/RECORD
