Metadata-Version: 2.4
Name: covalent-blueprints-ai
Version: 0.5.2
Summary: A collection of AI blueprints for Covalent Cloud.
Author-email: Agnostiq <support@agnostiq.ai>
Maintainer-email: Ara Ghukasyan <ara@agnostiq.ai>, Sankalp Sanand <sankalp@agnostiq.ai>
License:                                  Apache License
Project-URL: Homepage, https://github.com/AgnostiqHQ/covalent-blueprints-ai
Keywords: covalent,covalent-cloud,ai,blueprints,agnostiq
Classifier: Development Status :: 1 - Planning
Classifier: Environment :: Console
Classifier: Environment :: Plugins
Classifier: Intended Audience :: Developers
Classifier: Intended Audience :: Education
Classifier: Intended Audience :: Science/Research
Classifier: License :: Other/Proprietary License
Classifier: Natural Language :: English
Classifier: Operating System :: MacOS
Classifier: Operating System :: POSIX :: Linux
Classifier: Programming Language :: Python :: 3
Classifier: Programming Language :: Python :: 3 :: Only
Classifier: Programming Language :: Python :: 3.8
Classifier: Programming Language :: Python :: 3.9
Classifier: Programming Language :: Python :: 3.10
Classifier: Topic :: Adaptive Technologies
Classifier: Topic :: Scientific/Engineering
Classifier: Topic :: Scientific/Engineering :: Interface Engine/Protocol Translator
Classifier: Topic :: Software Development
Classifier: Topic :: System :: Distributed Computing
Requires-Python: >=3.8
License-File: LICENSE
Requires-Dist: covalent-blueprints>=0.8.1rc0
Requires-Dist: covalent-cloud>=1.1.0
Requires-Dist: snowflake-connector-python>=3.13.1
Dynamic: license-file
